dontimport/__init__.py
dontimport/__main__.py
dontimport-1.0.0.dist-info/METADATA
dontimport-1.0.0.dist-info/WHEEL
dontimport-1.0.0.dist-info/top_level.txt
dontimport-1.0.0.dist-info/RECORD
