Metadata-Version: 2.1
Name: dontimport
Version: 1.0.0
Summary: Don't import this package.
Home-page: https://github.com/SuperMaZingCoder/dontimport
Author: SuperMaZingCoder
Author-email: supermazingcoder@gmail.com
License: MIT
Platform: UNKNOWN
Classifier: License :: OSI Approved :: MIT License
Classifier: Programming Language :: Python :: 3
Classifier: Programming Language :: Python :: 3.7
